citizenshell/__init__.py
citizenshell/abstractremoteshell.py
citizenshell/abstractshell.py
citizenshell/adbshell.py
citizenshell/localshell.py
citizenshell/parseduri.py
citizenshell/queue.py
citizenshell/secureshell.py
citizenshell/serialshell.py
citizenshell/shell.py
citizenshell/shellerror.py
citizenshell/shellresult.py
citizenshell/streamreader.py
citizenshell/telnetshell.py
citizenshell-2.3.2.dist-info/LICENSE
citizenshell-2.3.2.dist-info/METADATA
citizenshell-2.3.2.dist-info/WHEEL
citizenshell-2.3.2.dist-info/top_level.txt
citizenshell-2.3.2.dist-info/RECORD
