Metadata-Version: 2.1
Name: citizenshell
Version: 2.3.2
Summary: Interact with shell locally or over different connection types (telnet, ssh, serial, adb)
Home-page: https://github.com/meuter/citizenshell
Author: Cedric Meuter
Author-email: cedric.meuter@gmail.com
License: MIT
Download-URL: https://github.com/meuter/citizenshell/archive/2.3.2.tar.gz
Keywords: shell,telnet,adb,ssh,serial
Platform: UNKNOWN
Classifier: Development Status :: 4 - Beta
Classifier: Environment :: Console
Classifier: Intended Audience :: Developers
Classifier: Intended Audience :: Information Technology
Classifier: License :: OSI Approved :: MIT License
Classifier: Operating System :: MacOS :: MacOS X
Classifier: Operating System :: POSIX
Classifier: Programming Language :: Python
Classifier: Programming Language :: Python :: 2
Classifier: Programming Language :: Python :: 2.7
Classifier: Programming Language :: Python :: 3
Classifier: Programming Language :: Python :: 3.4
Classifier: Programming Language :: Python :: 3.5
Classifier: Programming Language :: Python :: 3.6
Classifier: Programming Language :: Python :: 3.7
Classifier: Programming Language :: Python :: 3.8
Classifier: Topic :: Utilities
Requires-Dist: termcolor (>=1.1.0)
Requires-Dist: paramiko (>=2.4.0)
Requires-Dist: uritools (>=2.1.0)
Requires-Dist: pyserial (>=3.4)
Requires-Dist: scp (>=0.10.2)
Requires-Dist: backports.tempfile (>=0.4.0)
